playtest2/__about__.py
playtest2/__init__.py
playtest2/cli.py
playtest2/gauge_table.py
playtest2/steps/__init__.py
playtest2/steps/core.py
playtest2/steps/http.py
playtest2-0.0.5.dist-info/METADATA
playtest2-0.0.5.dist-info/WHEEL
playtest2-0.0.5.dist-info/entry_points.txt
playtest2-0.0.5.dist-info/licenses/LICENSE.txt
playtest2-0.0.5.dist-info/RECORD
