Metadata-Version: 2.4
Name: playtest2
Version: 0.0.5
Summary: Python port of uzabase/playtest2
Project-URL: Documentation, https://github.com/ftnext/playtest2-python#readme
Project-URL: Issues, https://github.com/ftnext/playtest2-python/issues
Project-URL: Source, https://github.com/ftnext/playtest2-python
Author-email: ftnext <takuyafjp+develop@gmail.com>
License-Expression: MIT
License-File: LICENSE.txt
Keywords: automation,gauge,gauge-python,testing
Classifier: Development Status :: 3 - Alpha
Classifier: Intended Audience :: Developers
Classifier: Programming Language :: Python
Classifier: Programming Language :: Python :: 3 :: Only
Classifier: Programming Language :: Python :: 3.9
Classifier: Programming Language :: Python :: 3.10
Classifier: Programming Language :: Python :: 3.11
Classifier: Programming Language :: Python :: 3.12
Classifier: Programming Language :: Python :: 3.13
Classifier: Topic :: Software Development :: Testing
Classifier: Topic :: Software Development :: Testing :: Acceptance
Requires-Python: >=3.9
Requires-Dist: getgauge
Requires-Dist: httpx
Requires-Dist: jsonpath-ng
